MANIFEST.in
README.md
setup.py
migc/__init__.py
migc/__version__.py
migc/cli.py
migc/exceptions.py
migc/help.py
migc/models.py
migc/status_codes.py
migc/utils.py
migc.egg-info/PKG-INFO
migc.egg-info/SOURCES.txt
migc.egg-info/dependency_links.txt
migc.egg-info/entry_points.txt
migc.egg-info/not-zip-safe
migc.egg-info/requires.txt
migc.egg-info/top_level.txt